calc/calculator.py
calc/dong_calculator.py
dong_calculator.py-0.0.0.dist-info/LICENSE
dong_calculator.py-0.0.0.dist-info/METADATA
dong_calculator.py-0.0.0.dist-info/WHEEL
dong_calculator.py-0.0.0.dist-info/top_level.txt
dong_calculator.py-0.0.0.dist-info/RECORD
