Metadata-Version: 2.1
Name: dong-calculator.py
Version: 0.0.0
Summary: lec-oss my calculator 0001
Home-page: https://github.com/Sindongyeob/lec-oss
Author: dongyeobsin
License-File: LICENSE
